{
  "@context": "https://bibdata.princeton.edu/context.json",
  "@id": "https://figgy.princeton.edu/catalog/0cc43bdb-ae21-47b2-90bc-bc21a18ee821",
  "title": [
    {
      "@value": "磧砂大藏經 : 六千三百六十二卷",
      "@language": "zho"
    },
    {
      "@value": "Qisha Da zang jing : liu qian san bai liu shi er juan",
      "@language": "zho-latn"
    }
  ],
  "language": "zho",
  "call_number": "TC513/2198",
  "extent": "5359 v. : ill. ; 30 cm.",
  "format": "Book",
  "type": "Sacred books",
  "description": [
    "藏本不完整. 存1479種, 6014 卷.",
    "561函.",
    "框高25公分, 6行17字, 上下單邊.",
    "經摺裝.",
    "以補版本, 異版本及鈔本配補.",
    "附錄共3件. 第1為I.V. Gillis等製表1冊,有胡适、屈萬里等手記, 34 cm；第2件依照《影印宋磧砂版大藏經目錄》與館藏子目核對,1冊, 有屈萬里1965年手記, 29 cm; 第3件館藏有圖及年代記錄, 在文件夾中, 14頁, 30 cm."
  ],
  "publisher": [
    "[Pingjiang Fu : Qisha Yan sheng yuan, Song Shaoding 4 nian i.e. 1231-Yuan Zhizhi 2 nian i.e. 1322]",
    "[平江府 : 磧砂延聖院, 宋紹定4年 i.e. 1231-元至治2年 i.e. 1322]"
  ],
  "subject": "Buddhism—Sacred books",
  "title_sort": "[Qisha Da zang jing : liu qian san bai liu shi er juan / Fazhong ... et al.].",
  "alternative": [
    "Qisha zang",
    "磧砂藏"
  ],
  "references": "書名及卷數等據《中國版刻圖錄》等參考書.",
  "contributor": [
    "磧砂延聖院"
  ],
  "created": "1231-01-01T00:00:00Z/1322-12-31T23:59:59Z",
  "date": "1231-1322",
  "identifier": [
    "ark:/88435/nk322j018"
  ],
  "location": [
    "HSVE TC513/2198"
  ],
  "edm_rights": {
    "@id": "http://rightsstatements.org/vocab/NKC/1.0/",
    "@type": "dcterms:RightsStatement",
    "pref_label": "No Known Copyright"
  },
  "memberOf": [
    {
      "@id": "https://figgy.princeton.edu/catalog/f08f6307-2956-4791-bea2-0fdb35baef35",
      "@type": "pcdm:Collection",
      "title": "East Asian Library Tables of Contents"
    }
  ]
}
